[{"id":532,"youtube_link":"https://www.youtube.com/watch?v=tollGa3S0o8","title":"All Too Well","preview":null,"artists":["Taylor Swift"],"spotify_id":"5enxwA8aAbwZbf5qCHORXi","positions":100},{"id":533,"youtube_link":"https://www.youtube.com/watch?v=esILLxHM92M","title":"Avalon (with Francesco Turrisi)","preview":"https://p.scdn.co/mp3-preview/6b84d0d28ca4bd141d33d6c36dd19147609de185?cid=bb69da722fdd419ebf5f4cb0b55bbfed","artists":["Rhiannon Giddens","Francesco Turrisi"],"spotify_id":"3cJI6VFdyRdriDVwB0sU3Y","positions":99},{"id":534,"youtube_link":"https://www.youtube.com/watch?v=_uBbRcVktzA","title":"Baby Grand","preview":"https://p.scdn.co/mp3-preview/bf0052b21be486743aa382f8da1d367eceb5c4e7?cid=bb69da722fdd419ebf5f4cb0b55bbfed","artists":["Anna B Savage"],"spotify_id":"1kXKjYKAuFxlvTabSXmQhC","positions":98},{"id":535,"youtube_link":"https://www.youtube.com/watch?v=6bN45f9NjlA","title":"Wockesha","preview":null,"artists":["Moneybagg Yo"],"spotify_id":"0nqhKXDjsyBMvbeWmgijD0","positions":97},{"id":536,"youtube_link":"https://www.youtube.com/watch?v=Vhatr4ksdLo","title":"Automate","preview":"https://p.scdn.co/mp3-preview/2a9e4017e186dd5eb36cf404a53dfb6aad570841?cid=bb69da722fdd419ebf5f4cb0b55bbfed","artists":["Snail Mail"],"spotify_id":"6ZXH6YfcouRBWanewWxuuz","positions":96},{"id":537,"youtube_link":"https://www.youtube.com/watch?v=y8trd3gjJt0","title":"Pepas","preview":"https://p.scdn.co/mp3-preview/890f6034cf93d666d0f89d5724430c6ddd276eb2?cid=bb69da722fdd419ebf5f4cb0b55bbfed","artists":["Farruko"],"spotify_id":"2B4GHvToeLTOBB4QLzW3Ni","positions":95},{"id":538,"youtube_link":"https://www.youtube.com/watch?v=vrOXdwYuWIk","title":"29","preview":null,"artists":["Carly Pearce"],"spotify_id":"3VGGcNF0O9loBSuLveZEUU","positions":94},{"id":539,"youtube_link":"https://www.youtube.com/watch?v=mEUl4DThSwE","title":"That Funny Feeling","preview":"https://p.scdn.co/mp3-preview/5d359f76cabadf93828bc66b96d946ea272cd2ee?cid=bb69da722fdd419ebf5f4cb0b55bbfed","artists":["Phoebe Bridgers"],"spotify_id":"30y5OpD8TPAru2wsyZDD4S","positions":93},{"id":540,"youtube_link":"https://www.youtube.com/watch?v=8IGDA8ZUQ08","title":"Starlight","preview":null,"artists":["Yola"],"spotify_id":"1R4nFxIiipVTeUSFdOnVIy","positions":92},{"id":541,"youtube_link":"https://www.youtube.com/watch?v=GtfvAZzVPHU","title":"Back Of My Hand","preview":"https://p.scdn.co/mp3-preview/0046673fccfa9c9d5830caf947226608a5338644?cid=bb69da722fdd419ebf5f4cb0b55bbfed","artists":["Bachelor","Jay Som","Palehound"],"spotify_id":"6AZ2df8r1eS355mpwOcZEB","positions":91},{"id":542,"youtube_link":"https://www.youtube.com/watch?v=n96u5qI1o8M","title":"X","preview":"https://p.scdn.co/mp3-preview/b2b3fb78fdd38b99e2bc0fc3cd68fe5914829bd6?cid=bb69da722fdd419ebf5f4cb0b55bbfed","artists":["Tinashe","Jeremih"],"spotify_id":"3LUvWNx3ceBjsOeuDOMEsl","positions":90},{"id":543,"youtube_link":"https://www.youtube.com/watch?v=an2gXf61lxA","title":"Drunk Voicemail","preview":"https://p.scdn.co/mp3-preview/11247653ad0729a11e65baf0265fc2710453d97b?cid=bb69da722fdd419ebf5f4cb0b55bbfed","artists":["Pom Pom Squad"],"spotify_id":"7vkPs35POG3GJvXgPGPuvo","positions":89},{"id":544,"youtube_link":"https://www.youtube.com/watch?v=wV7Od-jriP0","title":"Moments","preview":"https://p.scdn.co/mp3-preview/8776d5ac1363c0fc4d2fe4214fc4b3f7782ff787?cid=bb69da722fdd419ebf5f4cb0b55bbfed","artists":["Nas"],"spotify_id":"1fs6stCUbH1ACZbyrRT321","positions":88},{"id":545,"youtube_link":"https://www.youtube.com/watch?v=jybliV52rEs","title":"Two Black Churches: No. 2, The Rain","preview":"https://p.scdn.co/mp3-preview/b26c64472c780b9e733d3463e7c49cdc04893155?cid=bb69da722fdd419ebf5f4cb0b55bbfed","artists":["Shawn E. Okpebholo","Will Liverman","Paul Sánchez"],"spotify_id":"12GuF0wv5jko88HeZuP8Tp","positions":87},{"id":546,"youtube_link":"https://www.youtube.com/watch?v=tPL80EIxqec","title":"Way Out","preview":"https://p.scdn.co/mp3-preview/9bf72481cca7df3c734cddc64d894f73517d3d0e?cid=bb69da722fdd419ebf5f4cb0b55bbfed","artists":["Indigo De Souza"],"spotify_id":"6dkCcUhIXXozh2eznpqqbV","positions":86},{"id":547,"youtube_link":"https://www.youtube.com/watch?v=1NMZ0MpaEuY","title":"Headshots (4r Da Locals)","preview":"https://p.scdn.co/mp3-preview/39fc2e93f600bc554267ec31717ac8eba8df68d1?cid=bb69da722fdd419ebf5f4cb0b55bbfed","artists":["Isaiah Rashad"],"spotify_id":"2rFTRICumonxxZKxxfEu8R","positions":85},{"id":548,"youtube_link":"https://www.youtube.com/watch?v=Xmxcnf2v_gs","title":"STEREOTYPE","preview":"https://p.scdn.co/mp3-preview/98fdb0c3fd3c09520fe5683606a9903615eefb0a?cid=bb69da722fdd419ebf5f4cb0b55bbfed","artists":["STAYC"],"spotify_id":"2bZIDMpzVooosmPHn0tHnd","positions":84},{"id":549,"youtube_link":"https://www.youtube.com/watch?v=cbJnBeq0ExY","title":"Avernal Gate","preview":"https://p.scdn.co/mp3-preview/59788c980ab6785160ad0e1e0c8640ac3d4df623?cid=bb69da722fdd419ebf5f4cb0b55bbfed","artists":["Khemmis"],"spotify_id":"2XdUaiSuEVgSvNjTirgvfj","positions":83},{"id":550,"youtube_link":"https://www.youtube.com/watch?v=4m6Nyy-aWnI","title":"鯱","preview":"https://p.scdn.co/mp3-preview/36b64b981e5bff762a40c749c438f0c1e25f05c6?cid=bb69da722fdd419ebf5f4cb0b55bbfed","artists":["Yuta Orisaka"],"spotify_id":"2VAM60ieXSv8w5IFu32vt3","positions":82},{"id":551,"youtube_link":"https://www.youtube.com/watch?v=Bn8yYzRTxTY","title":"Microdosing","preview":"https://p.scdn.co/mp3-preview/1e2a913f0bcbedb218fd384614a0842ccec80714?cid=bb69da722fdd419ebf5f4cb0b55bbfed","artists":["UNIIQU3"],"spotify_id":"3Ja8QhpuhcE1arTLw92tMu","positions":81},{"id":125,"youtube_link":"https://www.youtube.com/watch?v=NJea386275c","title":"WUSYANAME (feat. Youngboy Never Broke Again & Ty Dolla $ign)","preview":"https://p.scdn.co/mp3-preview/9999aca88df04e91ab931243f3ea04eb30c2ed10?cid=bb69da722fdd419ebf5f4cb0b55bbfed","artists":["Tyler, The Creator","YoungBoy Never Broke Again","Ty Dolla $ign"],"spotify_id":"5B0kgjHULYJhAQkK5XsMoC","positions":80},{"id":552,"youtube_link":"https://www.youtube.com/watch?v=xJnQAzafaR0","title":"Saudade","preview":"https://p.scdn.co/mp3-preview/fa8eaa00d93bffe7932f9fe5fca596c4be45c574?cid=bb69da722fdd419ebf5f4cb0b55bbfed","artists":["Žibuoklė Martinaitytė","Lithuanian National Symphony Orchestra","Giedrė Šlekytė"],"spotify_id":"24qPgxW9rI2xn4Ja3RkdUI","positions":79},{"id":553,"youtube_link":"https://www.youtube.com/watch?v=pP9Bto5lOEQ","title":"Patria y Vida","preview":"https://p.scdn.co/mp3-preview/fc7d080f4592fa579fed9920ae1bd2556a6b1487?cid=bb69da722fdd419ebf5f4cb0b55bbfed","artists":["Yotuel","Gente De Zona","Descemer Bueno","Maykel Osorbo","El Funky"],"spotify_id":"1jOF5X4zw27t9LQltutz9f","positions":78},{"id":554,"youtube_link":"https://www.youtube.com/watch?v=fhadDGg9HIU","title":"Hit Like A Girl","preview":"https://p.scdn.co/mp3-preview/dffaea7f6fdb041014a00d254ef3841b69c9eb21?cid=bb69da722fdd419ebf5f4cb0b55bbfed","artists":["Meet Me @ The Altar"],"spotify_id":"3kfghhJVXyT2W2TlP2Vsw9","positions":77},{"id":555,"youtube_link":"https://www.youtube.com/watch?v=XhWvysQhciQ","title":"Ship of Theseus","preview":"https://p.scdn.co/mp3-preview/8009cb59f3c9ca5154400a8a25adda4a0b81985f?cid=bb69da722fdd419ebf5f4cb0b55bbfed","artists":["Zao"],"spotify_id":"5ttYGZDnF0Q8emH4og43eu","positions":76},{"id":556,"youtube_link":"https://www.youtube.com/watch?v=Jis2EuuxGnM","title":"Marchita","preview":"https://p.scdn.co/mp3-preview/9de39eda9aadac6d278f5daaf6f9063e735d4851?cid=bb69da722fdd419ebf5f4cb0b55bbfed","artists":["Silvana Estrada"],"spotify_id":"1iiP2uv1Tv4Hvmv3YBC7hC","positions":75},{"id":557,"youtube_link":"https://www.youtube.com/watch?v=q-74HTjRbuY","title":"Musician","preview":"https://p.scdn.co/mp3-preview/9d269410e9e995ed929fd3155f56a0e0cd9308b0?cid=bb69da722fdd419ebf5f4cb0b55bbfed","artists":["Porter Robinson"],"spotify_id":"6AIMGwDREa86WOdxIQj2S7","positions":74},{"id":558,"youtube_link":"https://www.youtube.com/watch?v=McMeNI9bVA8","title":"Hedera","preview":"https://p.scdn.co/mp3-preview/8560be87f64a72c94d4e9188dd2f433b337e3ceb?cid=bb69da722fdd419ebf5f4cb0b55bbfed","artists":["Lesley Flanigan","Recap"],"spotify_id":"0bOm0TmuEm8SmGjPzBjFYh","positions":73},{"id":559,"youtube_link":"https://www.youtube.com/watch?v=kwvlCxIsS3g","title":"UNISIL","preview":"https://p.scdn.co/mp3-preview/c83e80ed74b5214444ffd98a5aaf21c6084f816f?cid=bb69da722fdd419ebf5f4cb0b55bbfed","artists":["SOPHIE"],"spotify_id":"0oRzcIZcW4oB2K2XfB2Uky","positions":72},{"id":560,"youtube_link":"https://www.youtube.com/watch?v=y4QVtiObkTg","title":"Coronach","preview":"https://p.scdn.co/mp3-preview/5515efa485eaae68e0da9e0e07b4273eccd50888?cid=bb69da722fdd419ebf5f4cb0b55bbfed","artists":["Daniel Bachman"],"spotify_id":"0Ohu2VfOCAwpgx3EP6AzPR","positions":71},{"id":561,"youtube_link":"https://www.youtube.com/watch?v=rCiBgLOcuKU","title":"Up","preview":"https://p.scdn.co/mp3-preview/82ab65039386088fbe7371a66d2a77e8858302b3?cid=bb69da722fdd419ebf5f4cb0b55bbfed","artists":["Cardi B"],"spotify_id":"4x68ANg3fJgpzEqvNSCvWh","positions":70},{"id":562,"youtube_link":"https://www.youtube.com/watch?v=kUZS41hcAcI","title":"Fuck Him All Night","preview":"https://p.scdn.co/mp3-preview/c08bccc66b70f7abe10e43ece5e750cd993e6e88?cid=bb69da722fdd419ebf5f4cb0b55bbfed","artists":["Azealia Banks"],"spotify_id":"4vMZPiiWKgmjcUcJVdW6YD","positions":69},{"id":563,"youtube_link":"https://www.youtube.com/watch?v=d7vTtnevlO4","title":"Witchoo","preview":"https://p.scdn.co/mp3-preview/fddd853b2ce12940e64444187f64d54e4eabf4c6?cid=bb69da722fdd419ebf5f4cb0b55bbfed","artists":["Durand Jones & The Indications","Aaron Frazer"],"spotify_id":"2YKLbY7vNypzaCg6qpsxhe","positions":68},{"id":564,"youtube_link":"https://www.youtube.com/watch?v=BS3HgiHPYcs","title":"Body","preview":"https://p.scdn.co/mp3-preview/9138e7203300cc84754e7b0ac0717e324417707b?cid=bb69da722fdd419ebf5f4cb0b55bbfed","artists":["Russ Millions","Tion Wayne"],"spotify_id":"3CVb6hkMrlF7eHhXi5B3PZ","positions":66},{"id":565,"youtube_link":"https://www.youtube.com/watch?v=WmLJAiwi9cI","title":"Go Your Way","preview":null,"artists":["Robert Plant","Alison Krauss"],"spotify_id":"0HIZ1JRhI5GukIPW2vMzhc","positions":65},{"id":566,"youtube_link":"https://www.youtube.com/watch?v=yJuV8PDwvC8","title":"White Dress","preview":null,"artists":["Lana Del Rey"],"spotify_id":"4Hl9rOqYomojCmxYfr25im","positions":64},{"id":567,"youtube_link":"https://www.youtube.com/watch?v=0EVVKs6DQLo","title":"Kiss Me More (feat. SZA)","preview":"https://p.scdn.co/mp3-preview/43a9157b0d8e28bfbade57804a06344894336755?cid=bb69da722fdd419ebf5f4cb0b55bbfed","artists":["Doja Cat","SZA"],"spotify_id":"5cOyxjetBT7kRnqL68madd","positions":63},{"id":568,"youtube_link":"https://www.youtube.com/watch?v=6u1d3Y8SvOM","title":"To Lose You","preview":"https://p.scdn.co/mp3-preview/f4e76cca0ee7757216ef29fc6902c4668cfc0f64?cid=bb69da722fdd419ebf5f4cb0b55bbfed","artists":["Mannequin Pussy"],"spotify_id":"3uzb6hzu7Wy13AvE6UYiwM","positions":62},{"id":569,"youtube_link":"https://www.youtube.com/watch?v=eFu1P-BPglE","title":"good wife","preview":null,"artists":["Kacey Musgraves"],"spotify_id":"64PsLB0bc1LJoZwogWO3ok","positions":61},{"id":570,"youtube_link":"https://www.youtube.com/watch?v=0Kx3sobEBFE","title":"Don't Go Yet","preview":"https://p.scdn.co/mp3-preview/aa06e95a1fbb185b61373f4b7c5c053e86df5d96?cid=bb69da722fdd419ebf5f4cb0b55bbfed","artists":["Camila Cabello"],"spotify_id":"1058fW9H3fZA6QjYCdOBad","positions":60},{"id":571,"youtube_link":"https://www.youtube.com/watch?v=WY1bZjXKKWA","title":"La Perla","preview":"https://p.scdn.co/mp3-preview/02d833f19e3b60ec950e5673acf7a23c8da5adab?cid=bb69da722fdd419ebf5f4cb0b55bbfed","artists":["Sofia Kourtesis"],"spotify_id":"128Imu3Z7l234ihO6vktaQ","positions":59},{"id":572,"youtube_link":"https://www.youtube.com/watch?v=CUzUI2wcqLg","title":"GYALIS","preview":null,"artists":["Capella Grey"],"spotify_id":"3u4Hd1DiCFbc6jGyGACCjj","positions":58},{"id":573,"youtube_link":"https://www.youtube.com/watch?v=1zOeqwHu1Ss","title":"Iced Coffee","preview":"https://p.scdn.co/mp3-preview/38cbe13a2d6fba47e233cf20da2e4a74f7fb72d4?cid=bb69da722fdd419ebf5f4cb0b55bbfed","artists":["Larry June"],"spotify_id":"0utHJ4RKZ63FXOiY7Qlds0","positions":57},{"id":574,"youtube_link":"https://www.youtube.com/watch?v=INmtwZdm_eM","title":"Why The Bright Stars Glow","preview":null,"artists":["Valerie June"],"spotify_id":"0tno4ePIoMnTD5AeEEMezX","positions":56},{"id":575,"youtube_link":"https://www.youtube.com/watch?v=kZlwB4ih8iM","title":"Sacude","preview":null,"artists":["Xenia Rubinos"],"spotify_id":"70m5gmRvvhgrkQmt04uVh6","positions":55},{"id":576,"youtube_link":"https://www.youtube.com/watch?v=uxfjLdQAA4I","title":"Bussifame","preview":"https://p.scdn.co/mp3-preview/7fcbcf28ccfdd6f47de102695d4977d194dec2b2?cid=bb69da722fdd419ebf5f4cb0b55bbfed","artists":["Dawn Richard"],"spotify_id":"3bQWyx3JDz53yP2uij16Jj","positions":54},{"id":577,"youtube_link":"https://www.youtube.com/watch?v=RnRkwcTJi9I","title":"Notice","preview":"https://p.scdn.co/mp3-preview/045826afdd8935ef55a678f7d0f5bdd982c2ae74?cid=bb69da722fdd419ebf5f4cb0b55bbfed","artists":["Tammy Lakkis"],"spotify_id":"5L1JhzHqgGWBqIGDzWFGT2","positions":53},{"id":578,"youtube_link":"https://www.youtube.com/watch?v=C2oEeNlQeoQ","title":"SAD GIRLZ LUV MONEY Remix (feat. Kali Uchis and Moliy)","preview":"https://p.scdn.co/mp3-preview/5df5531fc845ca7dcc83da8faf484039605d2fe3?cid=bb69da722fdd419ebf5f4cb0b55bbfed","artists":["Amaarae","Kali Uchis","Moliy"],"spotify_id":"15HMh4yxdf4wyxSZSlOgGZ","positions":52},{"id":579,"youtube_link":"https://www.youtube.com/watch?v=aOPi0YkOkBM","title":"WHOLE LOTTA MONEY","preview":"https://p.scdn.co/mp3-preview/5b645be80c0a20c07a23379f436a901863e67b42?cid=bb69da722fdd419ebf5f4cb0b55bbfed","artists":["BIA"],"spotify_id":"4UDMuYtLW6AorHHVb5XHtM","positions":51},{"id":580,"youtube_link":"https://www.youtube.com/watch?v=MIIBsmpZKH4","title":"Mi Conga Es De Akokán","preview":"https://p.scdn.co/mp3-preview/0134fd7afbc95e889322dcbabe29872b6ad96c32?cid=bb69da722fdd419ebf5f4cb0b55bbfed","artists":["Orquesta Akokán"],"spotify_id":"6FJ0VplefpgvlK4sqzDwlE","positions":50},{"id":581,"youtube_link":"https://www.youtube.com/watch?v=bQpaWvPFx8A","title":"Jackie","preview":"https://p.scdn.co/mp3-preview/98cef858d65261ce0dd9e3ac888100192a8a5c60?cid=bb69da722fdd419ebf5f4cb0b55bbfed","artists":["Yves Tumor"],"spotify_id":"1tEePg2AqDdRWLgYovr3yE","positions":49},{"id":582,"youtube_link":"https://www.youtube.com/watch?v=lZizLbWxr_E","title":"Go Down Deh (feat. Shaggy and Sean Paul)","preview":"https://p.scdn.co/mp3-preview/473051b2b74224cdb2eacd1a122e4477f21b4e89?cid=bb69da722fdd419ebf5f4cb0b55bbfed","artists":["Spice","Shaggy","Sean Paul"],"spotify_id":"0VzBKgimNRMauaqzT2rEnS","positions":48},{"id":583,"youtube_link":"https://www.youtube.com/watch?v=zHGf6tmnLYE","title":"Woman","preview":"https://p.scdn.co/mp3-preview/c30f4a5971dcf5ac664350c5e96f16a6ab5330c8?cid=bb69da722fdd419ebf5f4cb0b55bbfed","artists":["Little Simz","Cleo Sol"],"spotify_id":"2ruY7BpsZRwr6UUzLeDSk1","positions":47},{"id":584,"youtube_link":"https://www.youtube.com/watch?v=Y9OMJ0HvPbk","title":"Motorbike","preview":null,"artists":["Leon Bridges"],"spotify_id":"6W2trGwkUVR8mwGSH4Ftpf","positions":46},{"id":585,"youtube_link":"https://www.youtube.com/watch?v=VR8ooa3G_5M","title":"Amoeba","preview":null,"artists":["Clairo"],"spotify_id":"0HAqq2GcQKyi3s87GuN7jU","positions":45},{"id":586,"youtube_link":"https://www.youtube.com/watch?v=3LJUvh3svCE","title":"fitt (with Amaarae)","preview":"https://p.scdn.co/mp3-preview/07ce5d7766bffd8090bb42d8cf4e5f6a026d2200?cid=bb69da722fdd419ebf5f4cb0b55bbfed","artists":["Dua Saleh","Amaarae"],"spotify_id":"7ulh0asPyRT8nEkh3qbjBc","positions":44},{"id":587,"youtube_link":"https://www.youtube.com/watch?v=jYhE7HNvA8E","title":"jordan","preview":null,"artists":["Joy Oladokun"],"spotify_id":"77wdEr25RcwuesF8ejXJhL","positions":43},{"id":588,"youtube_link":"https://www.youtube.com/watch?v=Z_VD2iVezLU","title":"JUNO","preview":"https://p.scdn.co/mp3-preview/b3795dbf11aa1ee4b603a0bc58fda5058e3e196e?cid=bb69da722fdd419ebf5f4cb0b55bbfed","artists":["BLACKSTARKIDS"],"spotify_id":"2lvjpsQWNSsPb9sCLtwmJD","positions":42},{"id":589,"youtube_link":"https://www.youtube.com/watch?v=UfVkpgXB8Fg","title":"RIGHT NOW (feat. Stove God Cooks & Jadakiss)","preview":"https://p.scdn.co/mp3-preview/0f8ff97ac7389ca7501290926ad9fcd57206d5f3?cid=bb69da722fdd419ebf5f4cb0b55bbfed","artists":["Westside Gunn","Stove God Cooks","Jadakiss"],"spotify_id":"4f7r6dRgC7e8XSoKHD1UpL","positions":41},{"id":590,"youtube_link":"https://www.youtube.com/watch?v=XPmu8MS_VjE","title":"Knife Talk (with 21 Savage ft. Project Pat)","preview":null,"artists":["Drake","21 Savage","Project Pat"],"spotify_id":"38OxzrXfvFjyKWtgAkWdOK","positions":40},{"id":591,"youtube_link":"https://www.youtube.com/watch?v=h_V2ccs_Urk","title":"Bunny Is A Rider","preview":"https://p.scdn.co/mp3-preview/87264f6fab26c7df0781950b9b2d9b8e8ad38948?cid=bb69da722fdd419ebf5f4cb0b55bbfed","artists":["Caroline Polachek"],"spotify_id":"1rYABrDmfqVmJMwaNJBUUb","positions":39},{"id":592,"youtube_link":"https://www.youtube.com/watch?v=sJnoW7pxETo","title":"Nausicaa","preview":null,"artists":["Sarah Kirkland Snider","Emily D'Angelo","Jonas Niederstadt","das freie orchester Berlin","Jarkko Riihimäki"],"spotify_id":"5H1qpNi0GutfXXgG7fYc6p","positions":38},{"id":593,"youtube_link":"https://www.youtube.com/watch?v=HJxC_FoBmGQ","title":"F.U.C.K.","preview":"https://p.scdn.co/mp3-preview/cb2fb5addde97695a70c3adfb675eb66a77cf1c0?cid=bb69da722fdd419ebf5f4cb0b55bbfed","artists":["Victoria Monét"],"spotify_id":"0iDuW211AjTsYDPsLxyqX4","positions":37},{"id":594,"youtube_link":"https://www.youtube.com/watch?v=p5l0Wu821Ww","title":"Formwela 10","preview":null,"artists":["Esperanza Spalding"],"spotify_id":"3FAR18vZle5UwJyNThFLAO","positions":36},{"id":595,"youtube_link":"https://www.youtube.com/watch?v=ayd3yWr4tqU","title":"Volví","preview":"https://p.scdn.co/mp3-preview/9ecddd098329e3d9a27c1d9bf668a7060d3eb476?cid=bb69da722fdd419ebf5f4cb0b55bbfed","artists":["Aventura","Bad Bunny"],"spotify_id":"2vmfvSoZBFAt9hhRoEByLi","positions":35},{"id":596,"youtube_link":"https://www.youtube.com/watch?v=J5AhU5Q7vH0","title":"Racist, Sexist Boy - Live at LA Public Library","preview":"https://p.scdn.co/mp3-preview/a1b65857c1add1af9ba93f2e3300f1699548d959?cid=bb69da722fdd419ebf5f4cb0b55bbfed","artists":["The Linda Lindas"],"spotify_id":"6GeiA9XxITMHM3jk1hkNjY","positions":34},{"id":597,"youtube_link":"https://www.youtube.com/watch?v=kjAuUXdSFaM","title":"Good Ones","preview":"https://p.scdn.co/mp3-preview/0e333a9c0fffdf0cdeef056e79a149e5f14a9416?cid=bb69da722fdd419ebf5f4cb0b55bbfed","artists":["Charli XCX"],"spotify_id":"6PZpNMstpIiRenGK5UyG5D","positions":33},{"id":598,"youtube_link":"https://www.youtube.com/watch?v=--14w5SOEUs","title":"Avalanche","preview":null,"artists":["Migos"],"spotify_id":"2aXLmOKI4FIh2bJqQe10RI","positions":32},{"id":599,"youtube_link":"https://www.youtube.com/watch?v=hXaPGlkd5do","title":"What It Is","preview":null,"artists":["Amber Mark"],"spotify_id":"2CJfHjywgcczXQi6Dosw8Q","positions":31},{"id":600,"youtube_link":"https://www.youtube.com/watch?v=u2egpSzhjsA","title":"713","preview":null,"artists":["James Francies"],"spotify_id":"5EWPXmBa949HMMe3s611CW","positions":30},{"id":601,"youtube_link":"https://www.youtube.com/watch?v=adLGHcj_fmA","title":"Leave The Door Open","preview":"https://p.scdn.co/mp3-preview/98f4a6a2e2c031e272ffc93c5fec5d7cb43de490?cid=bb69da722fdd419ebf5f4cb0b55bbfed","artists":["Bruno Mars","Anderson .Paak","Silk Sonic"],"spotify_id":"7MZGaPVXjo2mLgTW661eg4","positions":29},{"id":602,"youtube_link":"https://www.youtube.com/watch?v=Xo_lPnBlfto","title":"Just for me","preview":"https://p.scdn.co/mp3-preview/c9f694a4a34dfcc1a501cb877bb4156c788dbd43?cid=bb69da722fdd419ebf5f4cb0b55bbfed","artists":["PinkPantheress"],"spotify_id":"6OTKVgVpVaVjhRLYizPJKA","positions":28},{"id":603,"youtube_link":"https://www.youtube.com/watch?v=2dTMIH5gCHg","title":"Meet Me At Our Spot","preview":null,"artists":["THE ANXIETY","WILLOW","Tyler Cole"],"spotify_id":"07MDkzWARZaLEdKxo6yArG","positions":27},{"id":604,"youtube_link":"https://www.youtube.com/watch?v=fhyk9rchC2c","title":"Silk Chiffon (feat. Phoebe Bridgers)","preview":"https://p.scdn.co/mp3-preview/90b376937f88a747abad0095cf223ae443f2a65c?cid=bb69da722fdd419ebf5f4cb0b55bbfed","artists":["MUNA","Phoebe Bridgers"],"spotify_id":"0BLY78hYpsH9NqP6X0N8CX","positions":26},{"id":605,"youtube_link":"https://www.youtube.com/watch?v=GS4zsLNTPok","title":"YA","preview":"https://p.scdn.co/mp3-preview/92150673dd4b0c3f180e2877ba9d5736acc13416?cid=bb69da722fdd419ebf5f4cb0b55bbfed","artists":["YEИDRY"],"spotify_id":"1SItv3YEX2txYK9mkbSKqD","positions":25},{"id":606,"youtube_link":"https://www.youtube.com/watch?v=2ZfcZEIo6Bw","title":"Be Sweet","preview":null,"artists":["Japanese Breakfast"],"spotify_id":"2avbMHWObD8usXMBmN4U62","positions":24},{"id":607,"youtube_link":"https://www.youtube.com/watch?v=a3Z0iESwUcY","title":"Same Size Shoe","preview":null,"artists":["serpentwithfeet"],"spotify_id":"6K3uiKpdX4tt9cydvsh6Pn","positions":23},{"id":608,"youtube_link":"https://www.youtube.com/watch?v=E8lOTqG6miQ","title":"1","preview":"https://p.scdn.co/mp3-preview/94cfae4145201f330b4d2a25dc5d1242cd4a1341?cid=bb69da722fdd419ebf5f4cb0b55bbfed","artists":["Petal Supply","umru","Himera","trndytrndy"],"spotify_id":"7sYXudDYZ0RPA3V8UPTNek","positions":22},{"id":609,"youtube_link":"https://www.youtube.com/watch?v=Aoz_1RfjhkM","title":"Elyne Road","preview":"https://p.scdn.co/mp3-preview/b9bfe7369abd1be1854e82bd9d90a5fba42dc06d?cid=bb69da722fdd419ebf5f4cb0b55bbfed","artists":["Toumani Diabaté"],"spotify_id":"0A3E8E3CRhUPYYar0w2pqA","positions":21},{"id":610,"youtube_link":"https://www.youtube.com/watch?v=cii6ruuycQA","title":"deja vu","preview":null,"artists":["Olivia Rodrigo"],"spotify_id":"064H72BhK7FRuQKFqGMeDv","positions":20},{"id":611,"youtube_link":"https://www.youtube.com/watch?v=2pcsUJLRDjo","title":"Let 'Em Burn","preview":"https://p.scdn.co/mp3-preview/5ad6a1d8347cfd673ac7a1522065df5f2ce2a02f?cid=bb69da722fdd419ebf5f4cb0b55bbfed","artists":["Emily Scott Robinson"],"spotify_id":"2OKsROxAwX6NP3l5idWrna","positions":19},{"id":612,"youtube_link":"https://www.youtube.com/watch?v=hppSIHl2tp0","title":"Afrique Victime","preview":"https://p.scdn.co/mp3-preview/d9fe472f70275522505e090410a49a258354bc38?cid=bb69da722fdd419ebf5f4cb0b55bbfed","artists":["Mdou Moctar"],"spotify_id":"1RhL5PGWaiYXwVmqOpj0Nm","positions":18},{"id":613,"youtube_link":"https://www.youtube.com/watch?v=HYbXt4_r9Pw","title":"Working for the Knife","preview":"https://p.scdn.co/mp3-preview/bfeeb20dc149cba1c2ada3f94b5fe890ac4007c9?cid=bb69da722fdd419ebf5f4cb0b55bbfed","artists":["Mitski"],"spotify_id":"4r8iH80jmm4CFZHT2nE0WI","positions":17},{"id":614,"youtube_link":"https://www.youtube.com/watch?v=FjlwJwhRMd4","title":"How Much Can A Heart Take (feat. Yebba)","preview":"https://p.scdn.co/mp3-preview/879fde247732df1acf03d2ab6c970d28d741e1b6?cid=bb69da722fdd419ebf5f4cb0b55bbfed","artists":["Lucky Daye","Yebba"],"spotify_id":"5SFssNXGjeOxdAnECfgttm","positions":16},{"id":615,"youtube_link":"https://www.youtube.com/watch?v=ifH2e5YXjbc","title":"Grumpy Old Man","preview":null,"artists":["Remi Wolf"],"spotify_id":"0pbfNjEoyK0zuw1UW22FWw","positions":15},{"id":616,"youtube_link":"https://www.youtube.com/watch?v=lKYrGdvmeqc","title":"Rainforest","preview":"https://p.scdn.co/mp3-preview/451fc95260663c62162276731455a4fc868fd3a6?cid=bb69da722fdd419ebf5f4cb0b55bbfed","artists":["Noname"],"spotify_id":"7thhWP37F1tHFcrnwLNaao","positions":14},{"id":617,"youtube_link":"https://www.youtube.com/watch?v=aZkcF5lzN3k","title":"Higher","preview":"https://p.scdn.co/mp3-preview/55255a8aeca16998b3c293e0546ea0e187b762f9?cid=bb69da722fdd419ebf5f4cb0b55bbfed","artists":["Sun-El Musician","Simmy"],"spotify_id":"0rmFBhKvt0KZI10t2coIYK","positions":13},{"id":618,"youtube_link":"https://www.youtube.com/watch?v=IkuBYRUwWdg","title":"range brothers (with Kendrick Lamar)","preview":"https://p.scdn.co/mp3-preview/d0b5c3278860d65d758a0c1d16116f2db2f5290e?cid=bb69da722fdd419ebf5f4cb0b55bbfed","artists":["Baby Keem","Kendrick Lamar"],"spotify_id":"0UTyLmkQgPOEIz95OVAJTR","positions":12},{"id":619,"youtube_link":"https://www.youtube.com/watch?v=bhSa-ibhXjc","title":"Reclamation","preview":null,"artists":["Brandee Younger"],"spotify_id":"1KX0mYaAAO1PyFr2VSG2ob","positions":11},{"id":620,"youtube_link":"https://www.youtube.com/watch?v=odZCQhibzGM","title":"Broken Horses","preview":"https://p.scdn.co/mp3-preview/041737eb504a50ba68442745be12ae44c934744d?cid=bb69da722fdd419ebf5f4cb0b55bbfed","artists":["Brandi Carlile"],"spotify_id":"0vAGNjNpJhjZTxvtcGeAib","positions":10},{"id":621,"youtube_link":"https://www.youtube.com/watch?v=gNi_6U5Pm_o","title":"good 4 u","preview":null,"artists":["Olivia Rodrigo"],"spotify_id":"6P4d1NWBCNIYZjzF9k1mVN","positions":9},{"id":622,"youtube_link":"https://www.youtube.com/watch?v=FfesqRkdSEk","title":"Have Mercy","preview":"https://p.scdn.co/mp3-preview/11b8411fefbdf8cf3bb8be8adfbd6aa86f96a972?cid=bb69da722fdd419ebf5f4cb0b55bbfed","artists":["Chlöe"],"spotify_id":"5SixeLvPsYpk7qq9lo5xYg","positions":8},{"id":623,"youtube_link":"https://www.youtube.com/watch?v=CFPLIaMpGrY","title":"Todo De Ti","preview":"https://p.scdn.co/mp3-preview/2ab0e36f53ce0e8a216f99b81ffb8f9b65680c2b?cid=bb69da722fdd419ebf5f4cb0b55bbfed","artists":["Rauw Alejandro"],"spotify_id":"4fSIb4hdOQ151TILNsSEaF","positions":7},{"id":624,"youtube_link":"https://www.youtube.com/watch?v=eW8XoovSlsM","title":"Hard Drive - Security Guard","preview":"https://p.scdn.co/mp3-preview/ae026378486106352e13234bdfee716c48c24aa3?cid=bb69da722fdd419ebf5f4cb0b55bbfed","artists":["Cassandra Jenkins"],"spotify_id":"3Cd4tmKhLinAwa5YPdf9tx","positions":6},{"id":625,"youtube_link":"https://www.youtube.com/watch?v=5ibj87fwRaM","title":"Like I Used To","preview":null,"artists":["Sharon Van Etten","Angel Olsen"],"spotify_id":"2TJDEIb71icDq3v0LXEGib","positions":5},{"id":626,"youtube_link":"https://www.youtube.com/watch?v=KynkMn5Hv3Q","title":"Thot Shit","preview":"https://p.scdn.co/mp3-preview/ada9780e16e6b1aaebc488866b14a7416b159c6e?cid=bb69da722fdd419ebf5f4cb0b55bbfed","artists":["Megan Thee Stallion"],"spotify_id":"7joRf3mjT0jy68k7lxzUNn","positions":4},{"id":627,"youtube_link":"https://www.youtube.com/watch?v=S19BYUvnKjk","title":"Thumbs","preview":"https://p.scdn.co/mp3-preview/14dbdcc30a5ef816aa8915f544003a7a18772839?cid=bb69da722fdd419ebf5f4cb0b55bbfed","artists":["Lucy Dacus"],"spotify_id":"79pcC3KJRMA2L8xIb5mu3G","positions":3},{"id":117,"youtube_link":"https://www.youtube.com/watch?v=Zd9jeJk2UHQ","title":"Chaise Longue","preview":"https://p.scdn.co/mp3-preview/0a1534b179b809dfa3c5f6c380d0e7eb14d22f58?cid=bb69da722fdd419ebf5f4cb0b55bbfed","artists":["Wet Leg"],"spotify_id":"7iqAuZe5yS0suLQcFfVK39","positions":2},{"id":628,"youtube_link":"https://www.youtube.com/watch?v=6swmTBVI83k","title":"MONTERO (Call Me By Your Name)","preview":null,"artists":["Lil Nas X"],"spotify_id":"3BZEcbdtXQSo7OrvKRJ6mb","positions":1}]
