[{"id":1452,"youtube_link":"https://www.youtube.com/watch?v=dMcmQ-SZh84","title":"Stage of Love","preview":"https://p.scdn.co/mp3-preview/fd24196c889c5d660927d35e033e152ba29f837d?cid=bb69da722fdd419ebf5f4cb0b55bbfed","artists":["Mary Jane Dunphe"],"spotify_id":"0cGCjJdfiuMcIJzfmjbszC","positions":100},{"id":1453,"youtube_link":"https://www.youtube.com/watch?v=2bSmOoAXjc4","title":"La Alhambra","preview":"https://p.scdn.co/mp3-preview/06575cd8127186007d82aabd39827b13643250d2?cid=bb69da722fdd419ebf5f4cb0b55bbfed","artists":["Marina Herlop"],"spotify_id":"4Qof27HYNjISAVepmVBD7t","positions":99},{"id":1454,"youtube_link":"https://www.youtube.com/watch?v=3Wnso2A4PZE","title":"LADY GAGA","preview":"https://p.scdn.co/mp3-preview/ec439edcef8f1b71e88cfeb7d200db274901123b?cid=bb69da722fdd419ebf5f4cb0b55bbfed","artists":["Peso Pluma","Gabito Ballesteros","Junior H"],"spotify_id":"7mXuWTczZNxG5EDcjFEuJR","positions":98},{"id":1455,"youtube_link":"https://www.youtube.com/watch?v=xWPqPzBHR5w","title":"Delete It","preview":"https://p.scdn.co/mp3-preview/5c03716bc7b210397dc8569763244a03cec7e1b3?cid=bb69da722fdd419ebf5f4cb0b55bbfed","artists":["MSPAINT","Militarie Gun"],"spotify_id":"76Xc9akiu0f47F0hWf6nFJ","positions":97},{"id":1456,"youtube_link":"https://www.youtube.com/watch?v=mEenY7Ghvac","title":"Yeezy Boots","preview":"https://p.scdn.co/mp3-preview/929edd2fc3e9e333aa72a1cc8907058ed7e6fd71?cid=bb69da722fdd419ebf5f4cb0b55bbfed","artists":["RXKNephew"],"spotify_id":"1aIIVux2vfYTzOOKdEmXLF","positions":96},{"id":1457,"youtube_link":"https://www.youtube.com/watch?v=qhqpQiXnFx0","title":"Go Dig My Grave","preview":"https://p.scdn.co/mp3-preview/d5ec2a4207425de1d8cc553c393ec60459dac350?cid=bb69da722fdd419ebf5f4cb0b55bbfed","artists":["Lankum"],"spotify_id":"5FBto2Mh2gVkGWV0mRh0hg","positions":95},{"id":1458,"youtube_link":"https://www.youtube.com/watch?v=bef8QLNHubw","title":"WHERE SHE GOES","preview":"https://p.scdn.co/mp3-preview/1607a3ea1bd3c452f9535abac08978efdffbde5a?cid=bb69da722fdd419ebf5f4cb0b55bbfed","artists":["Bad Bunny"],"spotify_id":"2sTDlCxmuZCTDKKk9f1qus","positions":94},{"id":1459,"youtube_link":"https://www.youtube.com/watch?v=WyVyV44EujE","title":"New York Transit Queen","preview":"https://p.scdn.co/mp3-preview/5ed2169a1745566c8935f9bd2e9fb074bdcd83f6?cid=bb69da722fdd419ebf5f4cb0b55bbfed","artists":["Corinne Bailey Rae"],"spotify_id":"6CjJtGi2x7xiBghJ4E8YIN","positions":93},{"id":1460,"youtube_link":"https://www.youtube.com/watch?v=M6QKZJeK-5w","title":"Nothing Left To Lose","preview":null,"artists":["Everything But The Girl"],"spotify_id":"02zPsXmSUP6Rr1Z2w5KMpf","positions":92},{"id":1461,"youtube_link":"https://www.youtube.com/watch?v=gvlancaf9Mk","title":"Desolation's Flower","preview":"https://p.scdn.co/mp3-preview/43e74be20a7bac1b47fa08285e588711d60fba80?cid=bb69da722fdd419ebf5f4cb0b55bbfed","artists":["Ragana"],"spotify_id":"0Pj2GFeYXhR5aMYMqDvBSk","positions":91},{"id":1462,"youtube_link":"https://www.youtube.com/watch?v=728vP8jorLY","title":"Darkness, Darkness","preview":"https://p.scdn.co/mp3-preview/c4b00fd57b48890cff324d161d2df74305e68dc5?cid=bb69da722fdd419ebf5f4cb0b55bbfed","artists":["Kieran Hebden","William Tyler"],"spotify_id":"2ih7916Ch16x9n75yhc3Ok","positions":90},{"id":1463,"youtube_link":"https://www.youtube.com/watch?v=u42iwxnIVak","title":"Pa Que Baile","preview":"https://p.scdn.co/mp3-preview/7918e68ce34a4a0ab5ea8d1f3b3f9957daa8f6d6?cid=bb69da722fdd419ebf5f4cb0b55bbfed","artists":["Kiko el Crazy"],"spotify_id":"5QbTfjpkTL6rCcB9EPLzD8","positions":89},{"id":1464,"youtube_link":"https://www.youtube.com/watch?v=fM9qIFuCKK0","title":"Amapiano","preview":"https://p.scdn.co/mp3-preview/74f92e02e49c46662f64f355d612516a8c42d218?cid=bb69da722fdd419ebf5f4cb0b55bbfed","artists":["Asake","Olamide"],"spotify_id":"3GMdp6clyAh7wZWVYOtoS9","positions":88},{"id":1465,"youtube_link":"https://www.youtube.com/watch?v=tjXzcoSWnRc","title":"Face Down","preview":null,"artists":["City Girls"],"spotify_id":"0DEjFljgDbPjkm5460EJnA","positions":87},{"id":1466,"youtube_link":"https://www.youtube.com/watch?v=21xNk2eD77o","title":"VAMPIROS","preview":"https://p.scdn.co/mp3-preview/44d3602b83e3a7cd32a19f25734a9de36358f740?cid=bb69da722fdd419ebf5f4cb0b55bbfed","artists":["ROSALÍA","Rauw Alejandro"],"spotify_id":"3Eax1yebRxj6LSYpxE9Yd3","positions":86},{"id":1467,"youtube_link":"https://www.youtube.com/watch?v=i8Vgo5S-_NM","title":"Rumble","preview":"https://p.scdn.co/mp3-preview/eb79af9f809883de0632f02388ec354478612754?cid=bb69da722fdd419ebf5f4cb0b55bbfed","artists":["Skrillex","Fred again..","Flowdan"],"spotify_id":"1GfBLbAhZUWdseuDqhocmn","positions":85},{"id":1468,"youtube_link":"https://www.youtube.com/watch?v=MB-lykRnhYM","title":"Fruit Loop","preview":"https://p.scdn.co/mp3-preview/a28e420a91a64fa71a26dc37653ec9ab8d2473c4?cid=bb69da722fdd419ebf5f4cb0b55bbfed","artists":["Flo Milli"],"spotify_id":"33vja43HFRaIMHlCZ6fwab","positions":84},{"id":1469,"youtube_link":"https://www.youtube.com/watch?v=WpuFZa5ow8E","title":"Ebony Eye","preview":"https://p.scdn.co/mp3-preview/2b03385c48bc2ad1e339c6ecb886d23a911eb989?cid=bb69da722fdd419ebf5f4cb0b55bbfed","artists":["Yves Tumor"],"spotify_id":"2BpnrXMYUyXIuBBmEKX52U","positions":83},{"id":1470,"youtube_link":"https://www.youtube.com/watch?v=tvmUrOSahsc","title":"Johnny Dang (with Paul Wall & DRODi)","preview":null,"artists":["That Mexican OT","Paul Wall","DRODi"],"spotify_id":"1kwPxt35W7cG3rryxR48PO","positions":82},{"id":1471,"youtube_link":"https://www.youtube.com/watch?v=uHoZlaT7sy4","title":"Float (feat. Seun Kuti & Egypt 80)","preview":"https://p.scdn.co/mp3-preview/f8d0d4ec095c2b51ce2e4b4e220cc0be720a9036?cid=bb69da722fdd419ebf5f4cb0b55bbfed","artists":["Janelle Monáe","Seun Kuti","Egypt 80"],"spotify_id":"2GLN3KJjmFhXG8mHGr6II0","positions":81},{"id":1472,"youtube_link":"https://www.youtube.com/watch?v=_EKC7JLBaJ8","title":"Good Lies","preview":"https://p.scdn.co/mp3-preview/88797a4f7c89f29a5821c11d18f3d027acb4f771?cid=bb69da722fdd419ebf5f4cb0b55bbfed","artists":["Overmono"],"spotify_id":"1ZnghCVtXCrtmKJH32z4UK","positions":80},{"id":1473,"youtube_link":"https://www.youtube.com/watch?v=dUIFGq3ycFc","title":"uHhH HuH.Mp3","preview":"https://p.scdn.co/mp3-preview/3b6ea9c5ee7dcff6305bbe07b255b153bf4dd11e?cid=bb69da722fdd419ebf5f4cb0b55bbfed","artists":["TisaKorean"],"spotify_id":"7yh8Siq8QVMiQkNGZ0Ljmj","positions":79},{"id":1474,"youtube_link":"https://www.youtube.com/watch?v=RNh-6sNxx6A","title":"To be honest","preview":"https://p.scdn.co/mp3-preview/c2d6408c1b99c433ce303b11dc875da50a3d865e?cid=bb69da722fdd419ebf5f4cb0b55bbfed","artists":["Christine and the Queens"],"spotify_id":"4xUnyV9tORZnezQCvPLAq4","positions":78},{"id":1475,"youtube_link":"https://www.youtube.com/watch?v=G9RpHfPyEx8","title":"kisses","preview":null,"artists":["Slowdive"],"spotify_id":"2qUNrUbCYoUE6MsOR3tTD1","positions":77},{"id":1476,"youtube_link":"https://www.youtube.com/watch?v=n7mFBobUlIc","title":"THANK ALLAH","preview":"https://p.scdn.co/mp3-preview/41ce18077455190b5c854cc323f806f69c778124?cid=bb69da722fdd419ebf5f4cb0b55bbfed","artists":["Niontay"],"spotify_id":"6BYFGHDNPHwFLIsAA3aLLH","positions":76},{"id":1477,"youtube_link":"https://www.youtube.com/watch?v=-0ClksySAmw","title":"Maria - Live","preview":"https://p.scdn.co/mp3-preview/33e73f799a69b708b4ce1eaa3ed1068a06603ec8?cid=bb69da722fdd419ebf5f4cb0b55bbfed","artists":["Greg Mendez"],"spotify_id":"7sh1xqqO06QigikSR8Ng3T","positions":75},{"id":1478,"youtube_link":"https://www.youtube.com/watch?v=bdN4rdaNvNs","title":"None Of Us Have But A Little While","preview":"https://p.scdn.co/mp3-preview/ee0a5a9c0e0984cf0ce3b066e628d230255c4bad?cid=bb69da722fdd419ebf5f4cb0b55bbfed","artists":["Lonnie Holley","Sharon Van Etten"],"spotify_id":"3rc1rv4kb7oUM4LnLDjNMS","positions":74},{"id":1479,"youtube_link":"https://www.youtube.com/watch?v=C4DwV8J9wzA","title":"Census Designated","preview":"https://p.scdn.co/mp3-preview/597f4033f8cb872181b1229782c7e40667b7c853?cid=bb69da722fdd419ebf5f4cb0b55bbfed","artists":["Jane Remover"],"spotify_id":"5IhT2qYheXI0O2dHMmAb6B","positions":73},{"id":1480,"youtube_link":"https://www.youtube.com/watch?v=JnEKSardRI0","title":"2HUMPY Anthem","preview":"https://p.scdn.co/mp3-preview/2599b7ea3c4c1343e041068d754a44f5360593fd?cid=bb69da722fdd419ebf5f4cb0b55bbfed","artists":["Brock","2Rare","Bril","GE3Z","Jmoney","Dj Crazy"],"spotify_id":"06rsuhNPOMR9bo7HfLfwFn","positions":72},{"id":1481,"youtube_link":"https://www.youtube.com/watch?v=jsMwWGPWHq8","title":"MÁQUINA CULONA","preview":"https://p.scdn.co/mp3-preview/23ed2fba76d2de6c478f712ba6796a44ad263fdd?cid=bb69da722fdd419ebf5f4cb0b55bbfed","artists":["Ralphie Choo","Mura Masa"],"spotify_id":"5aCmvEtoqJvkuoHMaExANL","positions":71},{"id":1482,"youtube_link":"https://www.youtube.com/watch?v=chOV4ongHIU","title":"Name of God","preview":"https://p.scdn.co/mp3-preview/38076ef1e93f330992ea07d7cacafdf5f951221b?cid=bb69da722fdd419ebf5f4cb0b55bbfed","artists":["Mustafa"],"spotify_id":"6gOxexvj0mjwnRRrLXT1cB","positions":70},{"id":1483,"youtube_link":"https://www.youtube.com/watch?v=pSY3i5XHHXo","title":"Sprinter","preview":null,"artists":["Dave","Central Cee"],"spotify_id":"3EyjOXEMYKw6pjBKQGJNj2","positions":69},{"id":1484,"youtube_link":"https://www.youtube.com/watch?v=Ri-pr4Egzng","title":"Skeleton Is Walking","preview":null,"artists":["Blake Mills"],"spotify_id":"1yPAFxvSlKJsihtyEtrN7u","positions":68},{"id":1485,"youtube_link":"https://www.youtube.com/watch?v=Mt4Miu5PuZg","title":"Push Power ( a 1 )","preview":"https://p.scdn.co/mp3-preview/1e523156a79e95432b3241665a93ab2962c5dbec?cid=bb69da722fdd419ebf5f4cb0b55bbfed","artists":["Actress"],"spotify_id":"3CxqY8alAaElQnFt6mSk9K","positions":67},{"id":1486,"youtube_link":"https://www.youtube.com/watch?v=t6G9eEZtpxY","title":"Tiny Garden","preview":"https://p.scdn.co/mp3-preview/ac624681c2d2da6e2e0011bdd2198f61c8c2e905?cid=bb69da722fdd419ebf5f4cb0b55bbfed","artists":["Jamila Woods","duendita"],"spotify_id":"40ke1BOmv6yyUrfbchPr3P","positions":66},{"id":1487,"youtube_link":"https://www.youtube.com/watch?v=2e8s-8X_XII","title":"Shmackin Town","preview":"https://p.scdn.co/mp3-preview/29c1038a150efe7fa56e955172153e96b9aed1be?cid=bb69da722fdd419ebf5f4cb0b55bbfed","artists":["AyooLii"],"spotify_id":"3vYrlGfltxHyZeBFRT6wqo","positions":65},{"id":1488,"youtube_link":"https://www.youtube.com/watch?v=zBukbgTN0cE","title":"Moonlight","preview":null,"artists":["Kali Uchis"],"spotify_id":"07x6kQE1CHOND0gkAsG2W1","positions":64},{"id":1489,"youtube_link":"https://www.youtube.com/watch?v=8UEM0dKbzAA","title":"Blind","preview":"https://p.scdn.co/mp3-preview/fa005d647eeef59f724fa46dfde1b96a117ffbea?cid=bb69da722fdd419ebf5f4cb0b55bbfed","artists":["SZA"],"spotify_id":"1k903tSQLMEyI25Zk7Uu9q","positions":63},{"id":1490,"youtube_link":"https://www.youtube.com/watch?v=fG_wUDpuYIs","title":"Hunter","preview":"https://p.scdn.co/mp3-preview/a9b7bf9469f773c731326ea13865e6d39b2c42c8?cid=bb69da722fdd419ebf5f4cb0b55bbfed","artists":["Jess Williamson"],"spotify_id":"6MT3BGYBY4J7rbr4TEvqml","positions":62},{"id":1491,"youtube_link":"https://www.youtube.com/watch?v=h9eqGcij9W0","title":"Fentanyl Tester","preview":"https://p.scdn.co/mp3-preview/1ce26cf7ad168500fa6536b1d4c59c1bc0a2fef9?cid=bb69da722fdd419ebf5f4cb0b55bbfed","artists":["JPEGMAFIA","Danny Brown"],"spotify_id":"4pfhCrRk6P2tMU2D0Mb2z5","positions":61},{"id":1492,"youtube_link":"https://www.youtube.com/watch?v=Hf487OncN9o","title":"Pretty In Possible","preview":"https://p.scdn.co/mp3-preview/f372819a5daa62d29c295db2b30b8510afcc5dfe?cid=bb69da722fdd419ebf5f4cb0b55bbfed","artists":["Caroline Polachek"],"spotify_id":"4Q5LWPIKCuV6LRdDeqOYM7","positions":60},{"id":1493,"youtube_link":"https://www.youtube.com/watch?v=4Tm_42JFgi4","title":"Love Who We Are Meant To","preview":null,"artists":["Feist"],"spotify_id":"042NmcH9nGlTotDZf07f1w","positions":59},{"id":1494,"youtube_link":"https://www.youtube.com/watch?v=s5IGAuE4HQI","title":"Late Night Love","preview":"https://p.scdn.co/mp3-preview/5e151bd9fefa2be4c29bd164153291dc6fb6f094?cid=bb69da722fdd419ebf5f4cb0b55bbfed","artists":["Octo Octa"],"spotify_id":"0qFtIHwXKO5orVkasAHDlh","positions":58},{"id":1495,"youtube_link":"https://www.youtube.com/watch?v=MawwzCX1GGM","title":"eclipse de amor","preview":"https://p.scdn.co/mp3-preview/ad736d9ea2db4b2b42005e6cf0658b16c3249762?cid=bb69da722fdd419ebf5f4cb0b55bbfed","artists":["NOIA","Buscabulla"],"spotify_id":"6oU12RE1G6CxW8tHkYLiRl","positions":57},{"id":1434,"youtube_link":"https://www.youtube.com/watch?v=TxZwCpgxttQ","title":"Speed Drive (From Barbie The Album)","preview":"https://p.scdn.co/mp3-preview/bd0a080a87ce594303d57981d921d65e12af6599?cid=bb69da722fdd419ebf5f4cb0b55bbfed","artists":["Charli XCX"],"spotify_id":"5VxmI3IdgAxWVvUnJoLuY2","positions":56},{"id":1269,"youtube_link":"https://www.youtube.com/watch?v=FYlYaVvskJQ","title":"Gorilla","preview":"https://p.scdn.co/mp3-preview/5df935986acb28251c013d96f1ff881d1fc07918?cid=bb69da722fdd419ebf5f4cb0b55bbfed","artists":["Little Simz"],"spotify_id":"0pJO1tc1GpnxFyQp6Zp82r","positions":55},{"id":1496,"youtube_link":"https://www.youtube.com/watch?v=VS6ixn2berk","title":"Red Wine Supernova","preview":null,"artists":["Chappell Roan"],"spotify_id":"0eEXpE2WgW5cjuZVAuvuev","positions":54},{"id":1497,"youtube_link":"https://www.youtube.com/watch?v=sBtJ9_zTqdE","title":"Bending Hectic","preview":"https://p.scdn.co/mp3-preview/6a9228ac6a2774c0738ac5767efa031981f5542c?cid=bb69da722fdd419ebf5f4cb0b55bbfed","artists":["The Smile"],"spotify_id":"4bu8TK2wLMJGGFkmyztGcw","positions":53},{"id":1498,"youtube_link":"https://www.youtube.com/watch?v=RlPNh_PBZb4","title":"vampire","preview":null,"artists":["Olivia Rodrigo"],"spotify_id":"6gTWiKdbtjAdTYTv8IyIRr","positions":52},{"id":1499,"youtube_link":"https://www.youtube.com/watch?v=e_Ue_P7vcRE","title":"Blackbox Life Recorder 21f","preview":"https://p.scdn.co/mp3-preview/63825104a7d8a79ecf02a8e1890dccd8ff221868?cid=bb69da722fdd419ebf5f4cb0b55bbfed","artists":["Aphex Twin"],"spotify_id":"55q5FJy2MagUgplPVB0tjD","positions":51},{"id":1500,"youtube_link":"https://www.youtube.com/watch?v=Y8qZ22IFK6I","title":"Psychedelic Switch","preview":null,"artists":["Carly Rae Jepsen"],"spotify_id":"7zy2kNoeD72x2NEDaAsJOX","positions":50},{"id":1501,"youtube_link":"https://www.youtube.com/watch?v=ogYC-8hs870","title":"Spirit 2.0","preview":"https://p.scdn.co/mp3-preview/cbbff3e555cc24959378e6b9e53d02558f1d0830?cid=bb69da722fdd419ebf5f4cb0b55bbfed","artists":["Sampha"],"spotify_id":"3JKRuo3KhL39T6XWAXPohj","positions":49},{"id":1502,"youtube_link":"https://www.youtube.com/watch?v=C8Ct6P4k8Gc","title":"Installation","preview":"https://p.scdn.co/mp3-preview/9df96ce2869d19ed26a4c62a8a093b1d5ac61877?cid=bb69da722fdd419ebf5f4cb0b55bbfed","artists":["Pangaea"],"spotify_id":"5tMMwt4iwS2fVm7KmGjxH4","positions":48},{"id":1503,"youtube_link":"https://www.youtube.com/watch?v=xEse84Nd944","title":"The Gods Must Be Crazy","preview":"https://p.scdn.co/mp3-preview/613e66f12826423d8fb769fe372bd96bf42bddc9?cid=bb69da722fdd419ebf5f4cb0b55bbfed","artists":["Armand Hammer","billy woods","E L U C I D","El-P"],"spotify_id":"62ir3CludVLlbrXk6AOlGg","positions":47},{"id":1504,"youtube_link":"https://www.youtube.com/watch?v=1RFLY62LrH0","title":"Needs","preview":"https://p.scdn.co/mp3-preview/0405f385a15b7a7139997731501125556b87ca35?cid=bb69da722fdd419ebf5f4cb0b55bbfed","artists":["Tinashe"],"spotify_id":"6sg284TefDkBpFh0317Agp","positions":46},{"id":1505,"youtube_link":"https://www.youtube.com/watch?v=DJq6BgrEivY","title":"Younger & Dumber","preview":"https://p.scdn.co/mp3-preview/dc320145517e6e5bccf6434838cbac84088992b9?cid=bb69da722fdd419ebf5f4cb0b55bbfed","artists":["Indigo De Souza"],"spotify_id":"0EWHn0McVO8Ewbkqvh53AD","positions":45},{"id":1506,"youtube_link":"https://www.youtube.com/watch?v=-8ADWWaP6kg","title":"Blissda","preview":"https://p.scdn.co/mp3-preview/c047a7d7f5dfbd97a20814e6ee100f4af5727e9f?cid=bb69da722fdd419ebf5f4cb0b55bbfed","artists":["DJ Koze"],"spotify_id":"6cOie6oyMHzoVHLmpLfHN4","positions":44},{"id":1507,"youtube_link":"https://www.youtube.com/watch?v=1Fb2PETOKRg","title":"Mayors A Cop","preview":"https://p.scdn.co/mp3-preview/497ce2b51f3e2d03874a342ce2cd9313e767542e?cid=bb69da722fdd419ebf5f4cb0b55bbfed","artists":["MIKE","Wiki","The Alchemist"],"spotify_id":"20rhLRRW6I177TzqQBV93U","positions":43},{"id":1508,"youtube_link":"https://www.youtube.com/watch?v=-ZdpbE5W4xo","title":"Snowman","preview":null,"artists":["Blonde Redhead"],"spotify_id":"4oGfVF3hKD6gJ39D6LIBG8","positions":42},{"id":1509,"youtube_link":"https://www.youtube.com/watch?v=p6Cnazi_Fi0","title":"Padam Padam","preview":null,"artists":["Kylie Minogue"],"spotify_id":"3k0DJq2HdWJqnqor8NX0ac","positions":41},{"id":1510,"youtube_link":"https://www.youtube.com/watch?v=V8I7JGpeI-E","title":"Pinking Shears","preview":"https://p.scdn.co/mp3-preview/f51a6714f169076789361044e85c0981e0fee277?cid=bb69da722fdd419ebf5f4cb0b55bbfed","artists":["Mandy, Indiana"],"spotify_id":"5o0DaHxpDoNyUtrvjmlB5T","positions":40},{"id":1511,"youtube_link":"https://www.youtube.com/watch?v=r7QnY3RVwHE","title":"dickhead blues","preview":"https://p.scdn.co/mp3-preview/83d60c83338fad761c0721ec99031e580a6e52f8?cid=bb69da722fdd419ebf5f4cb0b55bbfed","artists":["Kara Jackson"],"spotify_id":"0b1MDxh1MD1dwHs3nczuW7","positions":39},{"id":1512,"youtube_link":"https://www.youtube.com/watch?v=sY9GQx9M0HE","title":"Set The Roof","preview":"https://p.scdn.co/mp3-preview/15b5018dd9c156eb574fc8c16ed729ef402a39f6?cid=bb69da722fdd419ebf5f4cb0b55bbfed","artists":["Hudson Mohawke","Nikki Nair","Tayla Parx"],"spotify_id":"3FiPLOhNiB2Ox4ut1jJxE2","positions":38},{"id":1513,"youtube_link":"https://www.youtube.com/watch?v=HJBbPyS68TE","title":"I've Got Me","preview":"https://p.scdn.co/mp3-preview/3861b5322d4117f6050f16f839a544d440de0577?cid=bb69da722fdd419ebf5f4cb0b55bbfed","artists":["Joanna Sternberg"],"spotify_id":"4IUPYB1d0CDKWKNYQtl6g3","positions":37},{"id":1514,"youtube_link":"https://www.youtube.com/watch?v=IOONDURvCYs","title":"WICKED GYAL","preview":"https://p.scdn.co/mp3-preview/bbc77fcb4be121d7bc5b253dd3071abc0569035f?cid=bb69da722fdd419ebf5f4cb0b55bbfed","artists":["BAMBII","Lady Lykez"],"spotify_id":"6CScshKnmMgbhcA5zjmiRj","positions":36},{"id":1515,"youtube_link":"https://www.youtube.com/watch?v=Czke8Hmc5rY","title":"Moonless","preview":"https://p.scdn.co/mp3-preview/2e9782574a98b281f3826c98bb42179fa74252e8?cid=bb69da722fdd419ebf5f4cb0b55bbfed","artists":["Julie Byrne"],"spotify_id":"3lCSiBordGtNz6yeF9JZA6","positions":35},{"id":1516,"youtube_link":"https://www.youtube.com/watch?v=-AoIWKYXlBE","title":"x w x","preview":"https://p.scdn.co/mp3-preview/c8912fe8a238c8bf900fbd17998fca8902456f83?cid=bb69da722fdd419ebf5f4cb0b55bbfed","artists":["yeule"],"spotify_id":"23M9FijuZP9MsVQrCLdqct","positions":34},{"id":1517,"youtube_link":"https://www.youtube.com/watch?v=tfOURyD7ljc","title":"For Granted","preview":"https://p.scdn.co/mp3-preview/c0cfbf1342887a3139c5bf07e50f2224a0610b76?cid=bb69da722fdd419ebf5f4cb0b55bbfed","artists":["Yaeji"],"spotify_id":"61h5rJ790Vov9ks2Vut5mo","positions":33},{"id":1518,"youtube_link":"https://www.youtube.com/watch?v=bIX_ouNJsTs","title":"Not Strong Enough","preview":null,"artists":["boygenius","Julien Baker","Phoebe Bridgers","Lucy Dacus"],"spotify_id":"5E2XQFCt0ymGgem7DBt37h","positions":32},{"id":1519,"youtube_link":"https://www.youtube.com/watch?v=Gh93FW4o8AM","title":"old place","preview":"https://p.scdn.co/mp3-preview/134ee06a2a54f7fe7e8e6ec0d3dbbc7e0bc4ac5e?cid=bb69da722fdd419ebf5f4cb0b55bbfed","artists":["Jim Legxacy"],"spotify_id":"4Jh96C8DDxAJFCrECbFvxP","positions":31},{"id":1520,"youtube_link":"https://www.youtube.com/watch?v=KdJ-Qwu3y4Y","title":"On My Mama","preview":"https://p.scdn.co/mp3-preview/ca58edf96434fe902d4ac82f91c578d9d8eccba5?cid=bb69da722fdd419ebf5f4cb0b55bbfed","artists":["Victoria Monét"],"spotify_id":"1o8Z7GD1CeOaVBEyuzu4HO","positions":30},{"id":1521,"youtube_link":"https://www.youtube.com/watch?v=DGaKVLFNWzs","title":"Three Drums","preview":"https://p.scdn.co/mp3-preview/9878124e77b4e76f952e3481411c6969c4956f28?cid=bb69da722fdd419ebf5f4cb0b55bbfed","artists":["Four Tet"],"spotify_id":"2FRIWWs5xxPoQrk5pMmsQN","positions":29},{"id":1522,"youtube_link":"https://www.youtube.com/watch?v=vx4kLgnFexo","title":"My Love Mine All Mine","preview":"https://p.scdn.co/mp3-preview/2f90c9a6a2b6e38554d3bc3cf7512c2c70ac67b9?cid=bb69da722fdd419ebf5f4cb0b55bbfed","artists":["Mitski"],"spotify_id":"3vkCueOmm7xQDoJ17W1Pm3","positions":28},{"id":1523,"youtube_link":"https://www.youtube.com/watch?v=UtfkrGRK8wA","title":"Hollywood Baby","preview":"https://p.scdn.co/mp3-preview/4329f09de1ac1efe9dd2324ae0841a10f30b4a07?cid=bb69da722fdd419ebf5f4cb0b55bbfed","artists":["100 gecs"],"spotify_id":"4fdYd34E5ooeWJx6sLGpLH","positions":27},{"id":1524,"youtube_link":"https://www.youtube.com/watch?v=8tdPKlYTWn4","title":"Barley","preview":"https://p.scdn.co/mp3-preview/5444af04855f2223720f67f405e90570db41e383?cid=bb69da722fdd419ebf5f4cb0b55bbfed","artists":["Water From Your Eyes"],"spotify_id":"27XmeyUl26m0KYMJx1Blsb","positions":26},{"id":1525,"youtube_link":"https://www.youtube.com/watch?v=rlcjvlF2d-4","title":"If I Don’t See You in the Future, I’ll See You in the Pasture","preview":"https://p.scdn.co/mp3-preview/768a78ee937c1e07d35590ff6c299f041b70a1e9?cid=bb69da722fdd419ebf5f4cb0b55bbfed","artists":["Cole Pulice"],"spotify_id":"0wVClkwkqEZbVqY5tmY0Hp","positions":25},{"id":1526,"youtube_link":"https://www.youtube.com/watch?v=lhrme-A2IUs","title":"Dreamliner","preview":"https://p.scdn.co/mp3-preview/384945540e71f52a7ce52f46a7874cb304dfbb8c?cid=bb69da722fdd419ebf5f4cb0b55bbfed","artists":["Avalon Emerson"],"spotify_id":"5LhNwK0hawsVqNsV5SqlHy","positions":24},{"id":1527,"youtube_link":"https://www.youtube.com/watch?v=Id5Mh2T7rWc","title":"SkeeYee","preview":"https://p.scdn.co/mp3-preview/11300b68d6a224d6b66f62657aa6ef6e51e1a406?cid=bb69da722fdd419ebf5f4cb0b55bbfed","artists":["Sexyy Red"],"spotify_id":"7icwQvajsokotDfM3tefW6","positions":23},{"id":1528,"youtube_link":"https://www.youtube.com/watch?v=tb47lqqF-v0","title":"Knockin - Live","preview":"https://p.scdn.co/mp3-preview/0cb092cde3894479a9740056c0a2635c4a2aa900?cid=bb69da722fdd419ebf5f4cb0b55bbfed","artists":["MJ Lenderman"],"spotify_id":"1jG1KuT4WsRTaRFGNepUNh","positions":22},{"id":1529,"youtube_link":"https://www.youtube.com/watch?v=EvgYIXc4JDA","title":"I Got Heaven","preview":"https://p.scdn.co/mp3-preview/37ca60fbfad9c102741395711dbfc602b0f20644?cid=bb69da722fdd419ebf5f4cb0b55bbfed","artists":["Mannequin Pussy"],"spotify_id":"3CsJjIyl2Y6jz08DUuMMz8","positions":21},{"id":1530,"youtube_link":"https://www.youtube.com/watch?v=_GT9SmA1vlI","title":"Contact","preview":"https://p.scdn.co/mp3-preview/a527d14b72108d7723b2a42939a6565300025cd7?cid=bb69da722fdd419ebf5f4cb0b55bbfed","artists":["Kelela"],"spotify_id":"6RlczF1bVrcf4f65qaXuoA","positions":20},{"id":1531,"youtube_link":"https://www.youtube.com/watch?v=ZXL_4Lv38nY","title":"I Believe","preview":"https://p.scdn.co/mp3-preview/4f8aa4c2203aabe0c4f77a86e3c56718fcf36040?cid=bb69da722fdd419ebf5f4cb0b55bbfed","artists":["Caroline Polachek"],"spotify_id":"6GqesoY3jZD9BqT1v4UEmk","positions":19},{"id":1532,"youtube_link":"https://www.youtube.com/watch?v=GjdtlFrI7N0","title":"Pet Rock","preview":"https://p.scdn.co/mp3-preview/932a979f2542a64e67d8d687c188d68c07be18ce?cid=bb69da722fdd419ebf5f4cb0b55bbfed","artists":["L'Rain"],"spotify_id":"5nvAWyXQfFexcvnbmdcgBg","positions":18},{"id":1533,"youtube_link":"https://www.youtube.com/watch?v=2oDSwJmm-g0","title":"Year Zero","preview":"https://p.scdn.co/mp3-preview/a84a0922469f349e2b2b4b56f17336f04409a24c?cid=bb69da722fdd419ebf5f4cb0b55bbfed","artists":["billy woods","Kenny Segal","Danny Brown"],"spotify_id":"4pepbIXjq5Thakr90P3VHq","positions":17},{"id":1534,"youtube_link":"https://www.youtube.com/watch?v=4Dk21erUpvw","title":"Co-Star","preview":null,"artists":["Amaarae"],"spotify_id":"2rYu4zr0jXGWAHmNdpQYsl","positions":16},{"id":1535,"youtube_link":"https://www.youtube.com/watch?v=Ka1vNzmD6JE","title":"Vampire Empire","preview":"https://p.scdn.co/mp3-preview/8fc598038caa44efe9b06857efbc5d277dcb1ab4?cid=bb69da722fdd419ebf5f4cb0b55bbfed","artists":["Big Thief"],"spotify_id":"0ToG55iJZCOzZkcpWbXxpW","positions":15},{"id":1536,"youtube_link":"https://www.youtube.com/watch?v=Yhivl6fln3s","title":"The Hillbillies","preview":"https://p.scdn.co/mp3-preview/878c8cf55d1eef4bf4cbe230e0ee42275c91d531?cid=bb69da722fdd419ebf5f4cb0b55bbfed","artists":["Baby Keem","Kendrick Lamar"],"spotify_id":"1h6w4POXM2LfG4ZD4xUfZQ","positions":14},{"id":1537,"youtube_link":"https://www.youtube.com/watch?v=xmfNMAdeao0","title":"Shiver","preview":"https://p.scdn.co/mp3-preview/73bcf56f9a7a6c43b3bc6b42b14a0a865260c645?cid=bb69da722fdd419ebf5f4cb0b55bbfed","artists":["Fever Ray"],"spotify_id":"02KyBO8Rkzhs65K9VKmMpQ","positions":13},{"id":1538,"youtube_link":"https://www.youtube.com/watch?v=F2cF9o7FuU4","title":"It Must Change","preview":"https://p.scdn.co/mp3-preview/33333515291233f6fd06b3f4b70ae5e55d72c405?cid=bb69da722fdd419ebf5f4cb0b55bbfed","artists":["ANOHNI","Antony and the Johnsons"],"spotify_id":"2rmZqNkj6fD8ZLWJaKmv4F","positions":12},{"id":1539,"youtube_link":"https://www.youtube.com/watch?v=NZE4vU0Oxjk","title":"Daddy","preview":"https://p.scdn.co/mp3-preview/bb19c19f3826141cd308dd46a233e5e5b2fe0bce?cid=bb69da722fdd419ebf5f4cb0b55bbfed","artists":["Nourished by Time"],"spotify_id":"3jKlmTVS7ym2axSs9OEcrT","positions":11},{"id":1540,"youtube_link":"https://www.youtube.com/watch?v=PjhTvsLesLo","title":"Making The Band (Danity Kane)","preview":"https://p.scdn.co/mp3-preview/c48c80625812de76c2e97381c15d635e8cb30cc6?cid=bb69da722fdd419ebf5f4cb0b55bbfed","artists":["Earl Sweatshirt"],"spotify_id":"2VSDVmmjXRy5PTGsbCJJvb","positions":10},{"id":1541,"youtube_link":"https://www.youtube.com/watch?v=b53QJYP-lqY","title":"Rush","preview":null,"artists":["Troye Sivan"],"spotify_id":"4ZnkygoWLzcGbQYCm3lkae","positions":9},{"id":1542,"youtube_link":"https://www.youtube.com/watch?v=CTi7e9gEpN4","title":"Chosen to Deserve","preview":"https://p.scdn.co/mp3-preview/ff31084f89ba6f3827e2659c532b0128412213d0?cid=bb69da722fdd419ebf5f4cb0b55bbfed","artists":["Wednesday"],"spotify_id":"1c2meJL1RaGILGSw9Lnj0P","positions":8},{"id":1543,"youtube_link":"https://www.youtube.com/watch?v=ArmDp-zijuc","title":"Super Shy","preview":"https://p.scdn.co/mp3-preview/dab062e2cc708a2680ce84953a3581c5a679a230?cid=bb69da722fdd419ebf5f4cb0b55bbfed","artists":["NewJeans"],"spotify_id":"5sdQOyqq2IDhvmx2lHOpwd","positions":7},{"id":1544,"youtube_link":"https://www.youtube.com/watch?v=MSRcC626prw","title":"Kill Bill","preview":"https://p.scdn.co/mp3-preview/b3107d6c900922bdea140c8062115a89f815444e?cid=bb69da722fdd419ebf5f4cb0b55bbfed","artists":["SZA"],"spotify_id":"1beXhBtdGk0JDfBkAnMxw6","positions":6},{"id":1545,"youtube_link":"https://www.youtube.com/watch?v=ZsJ-BHohXRI","title":"get him back!","preview":null,"artists":["Olivia Rodrigo"],"spotify_id":"4vTkieCtQPP9sFo4qVXdcP","positions":5},{"id":1546,"youtube_link":"https://www.youtube.com/watch?v=LqBdoyxddq4","title":"namesake","preview":"https://p.scdn.co/mp3-preview/f6a923033408817cd98e310a21150a49967d7d12?cid=bb69da722fdd419ebf5f4cb0b55bbfed","artists":["Noname"],"spotify_id":"5TAqSeSM6JI5AGAmMHoSAu","positions":4},{"id":1547,"youtube_link":"https://www.youtube.com/watch?v=OLeCIRC4taY","title":"Will Anybody Ever Love Me?","preview":"https://p.scdn.co/mp3-preview/3d4c86ea13e246dedc381bb2a9eb55880d6fa55d?cid=bb69da722fdd419ebf5f4cb0b55bbfed","artists":["Sufjan Stevens"],"spotify_id":"6GY4onk77lT1xcDHT9rsvh","positions":3},{"id":1548,"youtube_link":"https://www.youtube.com/watch?v=oftolPu9qp4","title":"Boy's a liar Pt. 2","preview":"https://p.scdn.co/mp3-preview/543d8d09a5530a1ab94dd0c6f83fc4ee3e0d7f96?cid=bb69da722fdd419ebf5f4cb0b55bbfed","artists":["PinkPantheress","Ice Spice"],"spotify_id":"6AQbmUe0Qwf5PZnt4HmTXv","positions":2},{"id":1549,"youtube_link":"https://www.youtube.com/watch?v=pYqky795R1s","title":"A&W","preview":null,"artists":["Lana Del Rey"],"spotify_id":"1wTopxO5eQBpxrBXPSbsUn","positions":1}]
